{"trial_id": "1", "hyperparameters": {"space": [{"class_name": "Int", "config": {"name": "units", "default": null, "conditions": [], "min_value": 32, "max_value": 128, "step": 32, "sampling": null}}, {"class_name": "Choice", "config": {"name": "dropout_rate", "default": 0.1, "conditions": [], "values": [0.1, 0.2, 0.5, 0.02], "ordered": true}}, {"class_name": "Choice", "config": {"name": "activation", "default": "elu", "conditions": [], "values": ["elu", "relu", "leaky_relu"], "ordered": false}}, {"class_name": "Choice", "config": {"name": "learning_rate", "default": 0.05, "conditions": [], "values": [0.05, 0.001, 0.002], "ordered": true}}, {"class_name": "Choice", "config": {"name": "optimizer", "default": "Adam", "conditions": [], "values": ["Adam", "RMSprop", "Adadelta"], "ordered": false}}], "values": {"units": 96, "dropout_rate": 0.1, "activation": "leaky_relu", "learning_rate": 0.002, "optimizer": "Adadelta"}}, "metrics": {"metrics": {"loss": {"direction": "min", "observations": [{"value": [0.08936235308647156], "step": 29}]}, "mse": {"direction": "min", "observations": [{"value": [0.08936235308647156], "step": 29}]}, "val_loss": {"direction": "min", "observations": [{"value": [0.09680280089378357], "step": 29}]}, "val_mse": {"direction": "min", "observations": [{"value": [0.09680280089378357], "step": 29}]}}}, "score": 0.09680280089378357, "best_step": 29, "status": "COMPLETED"}